veribool/__init__.py
veribool/compiler.py
veribool/verifier.py
veribool-0.0.0.dist-info/LICENSE
veribool-0.0.0.dist-info/METADATA
veribool-0.0.0.dist-info/WHEEL
veribool-0.0.0.dist-info/entry_points.txt
veribool-0.0.0.dist-info/top_level.txt
veribool-0.0.0.dist-info/RECORD
