Metadata-Version: 2.1
Name: veribool
Version: 0.0.0
Summary: Verify various properties of boolean expressions using a concise DSL.
Author-email: Ronak Badhe <ronak.badhe@gmail.com>
License: MIT License
Project-URL: Homepage, https://github.com/r2dev2/veribool
Project-URL: Repository, https://github.com/r2dev2/veribool
Project-URL: Issues, https://github.com/r2dev2/veribool/issues
Keywords: compiler,verification,dsl,boolean,logic
Classifier: Programming Language :: Python :: 3
Classifier: Programming Language :: Python :: 3.10
Classifier: Programming Language :: Python :: 3.11
Classifier: Programming Language :: Python :: 3.12
Classifier: License :: OSI Approved :: MIT License
Classifier: Operating System :: OS Independent
Requires-Python: >=3.10
License-File: LICENSE
